teamscale_precommit_client/__init__.py
teamscale_precommit_client/client_configuration_utils.py
teamscale_precommit_client/data.py
teamscale_precommit_client/git_utils.py
teamscale_precommit_client/precommit_client.py
teamscale_cli-9.1.2.dist-info/LICENSE
teamscale_cli-9.1.2.dist-info/METADATA
teamscale_cli-9.1.2.dist-info/WHEEL
teamscale_cli-9.1.2.dist-info/entry_points.txt
teamscale_cli-9.1.2.dist-info/top_level.txt
teamscale_cli-9.1.2.dist-info/RECORD
