Metadata-Version: 2.1
Name: teamscale-cli
Version: 9.1.2
Summary: Client for performing precommit analysis with Teamscale.
Home-page: https://github.com/cqse/teamscale-cli
Author: Thomas Kinnen - CQSE GmbH
Author-email: kinnen@cqse.eu
License: Apache
Keywords: teamscale client precommit
Classifier: Topic :: Utilities
License-File: LICENSE
Requires-Dist: teamscale-client (==7.1.1)
Requires-Dist: gitpython (==3.1.35)
Requires-Dist: gitdb2 (==4.0.2)
Requires-Dist: nuitka (==1.8.2)
